CHANGES.txt
HACKING.txt
MANIFEST.in
pytest.ini
requirements.txt
setup.py
src/fc.agent.egg-info/PKG-INFO
src/fc.agent.egg-info/SOURCES.txt
src/fc.agent.egg-info/dependency_links.txt
src/fc.agent.egg-info/entry_points.txt
src/fc.agent.egg-info/namespace_packages.txt
src/fc.agent.egg-info/not-zip-safe
src/fc.agent.egg-info/requires.txt
src/fc.agent.egg-info/top_level.txt
src/gocept/__init__.py
src/gocept/net/__init__.py
src/gocept/net/configfile.py
src/gocept/net/conftest.py
src/gocept/net/dhcp.py
src/gocept/net/directory.py
src/gocept/net/ldaptools.py
src/gocept/net/passwd.py
src/gocept/net/utils.py
src/gocept/net/xmlrpc.py
src/gocept/net/ceph/__init__.py
src/gocept/net/ceph/cluster.py
src/gocept/net/ceph/pools.py
src/gocept/net/ceph/rbdimage.py
src/gocept/net/ceph/utils.py
src/gocept/net/ceph/tests/__init__.py
src/gocept/net/ceph/tests/cluster_test.py
src/gocept/net/ceph/tests/test_pools.py
src/gocept/net/ceph/tests/test_rbdimage.py
src/gocept/net/ceph/tests/fixtures/ceph.conf
src/gocept/net/configure/__init__.py
src/gocept/net/configure/backy.py
src/gocept/net/configure/bacula.py
src/gocept/net/configure/box.py
src/gocept/net/configure/ceph.py
src/gocept/net/configure/dhcpd.py
src/gocept/net/configure/iptables.py
src/gocept/net/configure/kibana.py
src/gocept/net/configure/kvm.py
src/gocept/net/configure/nagios.py
src/gocept/net/configure/postfix.py
src/gocept/net/configure/puppetmaster.py
src/gocept/net/configure/resize2fs.py
src/gocept/net/configure/users.py
src/gocept/net/configure/vmimages.py
src/gocept/net/configure/zones.py
src/gocept/net/configure/tests/__init__.py
src/gocept/net/configure/tests/test_backy.py
src/gocept/net/configure/tests/test_bacula.py
src/gocept/net/configure/tests/test_ceph.py
src/gocept/net/configure/tests/test_dhcpd.py
src/gocept/net/configure/tests/test_kvm.py
src/gocept/net/configure/tests/test_nagios.py
src/gocept/net/configure/tests/test_puppetmaster.py
src/gocept/net/configure/tests/test_user.py
src/gocept/net/configure/tests/test_vmimages.py
src/gocept/net/configure/tests/test_zones.py
src/gocept/net/configure/tests/fixtures/configure-zones.cfg
src/gocept/net/maintenance/__init__.py
src/gocept/net/maintenance/reqmanager.py
src/gocept/net/maintenance/request.py
src/gocept/net/maintenance/script.py
