Metadata-Version: 2.1
Name: fc.agent
Version: 1.10.12
Summary: Local configuration utilities and helper APIs for flyingcircus.io system configuration.
Home-page: http://github.com/flyingcircusio/fc.agent
Author: Flying Circus
Author-email: mail@flyingcircus.io
License: BSD
Platform: UNKNOWN
Classifier: Development Status :: 5 - Production/Stable
Classifier: Environment :: Console
Classifier: Programming Language :: Python :: 2.7
Provides-Extra: test
